[{"id":"15940001","download_url":"https://images.pexels.com/photos/15940001/pexels-photo-15940001.jpeg?auto=compress&cs=tinysrgb&dpr=2&h=650&w=940","source_url":"https://www.pexels.com/zh-cn/photo/15940001/","photographer":"Airam Dato-on","provider":"pexels","alt":"3C用品, 上網, 主屏幕 的 免费素材图片","filename":"cover.webp","query":"ai reading world news watchlist quiet editorial photo","local_path":"source/images/ai-reading-world-news-watchlist/cover.webp"},{"id":"31416361","download_url":"https://images.pexels.com/photos/31416361/pexels-photo-31416361.jpeg?auto=compress&cs=tinysrgb&dpr=2&h=650&w=940","source_url":"https://www.pexels.com/zh-cn/photo/31416361/","photographer":"Kuma Jio","provider":"pexels","alt":"黄昏时分东京港区的鸟瞰图，云层壮丽，城市灯光璀璨。","filename":"fig-01.webp","query":"ai reading world news watchlist city reflection editorial photo","local_path":"source/images/ai-reading-world-news-watchlist/fig-01.webp"},{"id":"16094048","download_url":"https://images.pexels.com/photos/16094048/pexels-photo-16094048.jpeg?auto=compress&cs=tinysrgb&dpr=2&h=650&w=940","source_url":"https://www.pexels.com/zh-cn/photo/16094048/","photographer":"Matheus Bertelli","provider":"pexels","alt":"＃室内, 3C用品, AI界面 的 免费素材图片","filename":"fig-02.webp","query":"ai reading world news watchlist workspace documents editorial photo","local_path":"source/images/ai-reading-world-news-watchlist/fig-02.webp"},{"id":"15983513","download_url":"https://images.pexels.com/photos/15983513/pexels-photo-15983513.jpeg?auto=compress&cs=tinysrgb&dpr=2&h=650&w=940","source_url":"https://www.pexels.com/zh-cn/photo/15983513/","photographer":"yanping ma","provider":"pexels","alt":"beach, beauty, book 的 免费素材图片","filename":"fig-03.webp","query":"ai reading world news watchlist person silhouette screen editorial photo","local_path":"source/images/ai-reading-world-news-watchlist/fig-03.webp"},{"id":"3473492","download_url":"https://images.pexels.com/photos/3473492/pexels-photo-3473492.jpeg?auto=compress&cs=tinysrgb&dpr=2&h=650&w=940","source_url":"https://www.pexels.com/zh-cn/photo/3473492/","photographer":"Elijah O'Donnell","provider":"pexels","alt":"黑人读报纸","filename":"fig-04.webp","query":"ai reading world news watchlist newspaper table morning light","local_path":"source/images/ai-reading-world-news-watchlist/fig-04.webp"},{"id":"16027824","download_url":"https://images.pexels.com/photos/16027824/pexels-photo-16027824.jpeg?auto=compress&cs=tinysrgb&dpr=2&h=650&w=940","source_url":"https://www.pexels.com/zh-cn/photo/16027824/","photographer":"Matheus Bertelli","provider":"pexels","alt":"AI模块, 互聯網, 人工智慧 的 免费素材图片","filename":"fig-05.webp","query":"ai reading world news watchlist abstract technology editorial photo","local_path":"source/images/ai-reading-world-news-watchlist/fig-05.webp"}]