[
  {
    "id": "4712308",
    "download_url": "https://images.pexels.com/photos/4712308/pexels-photo-4712308.jpeg?auto=compress&cs=tinysrgb&dpr=2&h=650&w=940",
    "source_url": "https://www.pexels.com/zh-cn/photo/4712308/",
    "photographer": "Daniel Bretas",
    "provider": "pexels",
    "alt": "es, espirito santo, 假期 的 免费素材图片",
    "filename": "cover.webp",
    "query": "self and era fear of being ordinary quiet editorial photo",
    "local_path": "source/images/self-and-era-fear-of-being-ordinary/cover.webp"
  },
  {
    "id": "18795990",
    "download_url": "https://images.pexels.com/photos/18795990/pexels-photo-18795990.jpeg?auto=compress&cs=tinysrgb&dpr=2&h=650&w=940",
    "source_url": "https://www.pexels.com/zh-cn/photo/18795990/",
    "photographer": "Farhad Irani",
    "provider": "pexels",
    "alt": "türkiye的, 中东, 人 的 免费素材图片",
    "filename": "fig-01.webp",
    "query": "self and era fear of being ordinary city reflection editorial photo",
    "local_path": "source/images/self-and-era-fear-of-being-ordinary/fig-01.webp"
  },
  {
    "id": "16150402",
    "download_url": "https://images.pexels.com/photos/16150402/pexels-photo-16150402.jpeg?auto=compress&cs=tinysrgb&dpr=2&h=650&w=940",
    "source_url": "https://www.pexels.com/zh-cn/photo/16150402/",
    "photographer": "Kiazoldyck",
    "provider": "pexels",
    "alt": "black and white, cafe, coffee 的 免费素材图片",
    "filename": "fig-02.webp",
    "query": "self and era fear of being ordinary workspace documents editorial photo",
    "local_path": "source/images/self-and-era-fear-of-being-ordinary/fig-02.webp"
  },
  {
    "id": "7102307",
    "download_url": "https://images.pexels.com/photos/7102307/pexels-photo-7102307.jpeg?auto=compress&cs=tinysrgb&dpr=2&h=650&w=940",
    "source_url": "https://www.pexels.com/zh-cn/photo/7102307/",
    "photographer": "Mozhgan Elahi",
    "provider": "pexels",
    "alt": "snapseed中, 内省, 创意摄影 的 免费素材图片",
    "filename": "fig-03.webp",
    "query": "self and era fear of being ordinary person silhouette screen editorial photo",
    "local_path": "source/images/self-and-era-fear-of-being-ordinary/fig-03.webp"
  },
  {
    "id": "8572138",
    "download_url": "https://images.pexels.com/photos/8572138/pexels-photo-8572138.jpeg?auto=compress&cs=tinysrgb&dpr=2&h=650&w=940",
    "source_url": "https://www.pexels.com/zh-cn/photo/8572138/",
    "photographer": "cottonbro studio",
    "provider": "pexels",
    "alt": "人, 企業, 休閒 的 免费素材图片",
    "filename": "fig-04.webp",
    "query": "personal success city life morning newspaper",
    "local_path": "source/images/self-and-era-fear-of-being-ordinary/fig-04.webp"
  },
  {
    "id": "33497533",
    "download_url": "https://images.pexels.com/photos/33497533/pexels-photo-33497533.jpeg?auto=compress&cs=tinysrgb&dpr=2&h=650&w=940",
    "source_url": "https://www.pexels.com/zh-cn/photo/33497533/",
    "photographer": "Thinh Phan Quoc",
    "provider": "pexels",
    "alt": "沉思的男人凝视着窗外的黑白画面",
    "filename": "fig-05.webp",
    "query": "quiet person city window reflection",
    "local_path": "source/images/self-and-era-fear-of-being-ordinary/fig-05.webp"
  }
]
